tests/__init__.py
tests/test_initial.py
workingtime/__init__.py
workingtime/workingtime.py
workingtime-0.2.0.dist-info/LICENSE
workingtime-0.2.0.dist-info/METADATA
workingtime-0.2.0.dist-info/WHEEL
workingtime-0.2.0.dist-info/top_level.txt
workingtime-0.2.0.dist-info/RECORD
